{
    "properties": {
        "template": {
            "title": "Template",
            "type": "string"
        },
        "static": {
            "title": "Static",
            "type": "object"
        },
        "states": {
            "title": "States",
            "type": "object"
        },
        "comp": {
            "anyOf": [
                {
                    "type": "object"
                },
                {
                    "additionalProperties": {
                        "type": "object"
                    },
                    "type": "object"
                }
            ],
            "title": "Comp"
        },
        "time": {
            "title": "Time",
            "type": "object"
        },
        "dynamic": {
            "anyOf": [
                {
                    "additionalProperties": {
                        "type": "object"
                    },
                    "type": "object"
                },
                {
                    "type": "null"
                }
            ],
            "default": null,
            "title": "Dynamic"
        },
        "_type": {
            "const": "scale.olm.generate.root:jt_expander",
            "title": "Olm Redirect Type"
        }
    },
    "required": [
        "template",
        "static",
        "states",
        "comp",
        "time",
        "_type"
    ],
    "title": "jt_expander",
    "type": "object",
    "$$description": [
        "Specified with :code:`\"_type\": \"scale.olm.generate.root:jt_expander\"` in **config.olm.json**.",
        "",
        ".. collapse:: Example input in config.olm.json/generate/root",
        "",
        "    .. code:: JSON",
        "",
        "",
        "        {",
        "            \"_type\": \"scale.olm.generate.root:jt_expander\",",
        "            \"template\": \"\",",
        "            \"static\": {",
        "                \"_type\": \"scale.olm.generate.static:pass_through\",",
        "                \"addnux\": 2,",
        "                \"xslib\": \"v7.1\"",
        "            },",
        "            \"states\": {",
        "                \"_type\": \"scale.olm.generate.states:full_hypercube\",",
        "                \"coolant_density\": [",
        "                    0.4,",
        "                    0.7,",
        "                    1.0",
        "                ],",
        "                \"enrichment\": [",
        "                    1.5,",
        "                    3.5,",
        "                    4.5",
        "                ],",
        "                \"specific_power\": [",
        "                    42.0",
        "                ]",
        "            },",
        "            \"comp\": {",
        "                \"fuel\": {",
        "                    \"_type\": \"scale.olm.generate.comp:uo2_simple\"",
        "                }",
        "            },",
        "            \"time\": {",
        "                \"_type\": \"scale.olm.generate.time:constpower_burndata\",",
        "                \"gwd_burnups\": [",
        "                    0,",
        "                    10,",
        "                    30,",
        "                    60",
        "                ]",
        "            },",
        "            \"dynamic\": {",
        "                \"z1\": {",
        "                    \"_type\": \"scale.olm.generate.dynamic:scipy_interp\",",
        "                    \"state_var\": \"coolant_density\",",
        "                    \"data_pairs\": [",
        "                        [",
        "                            0.3,",
        "                            0.4",
        "                        ],",
        "                        [",
        "                            0.7,",
        "                            0.5",
        "                        ],",
        "                        [",
        "                            1.1,",
        "                            0.6",
        "                        ]",
        "                    ],",
        "                    \"method\": \"pchip\"",
        "                }",
        "            }",
        "        }",
        "",
        ".. only::latex",
        "",
        "    END Example input in config.olm.json/generate/root",
        "",
        "",
        "",
        ".. collapse:: Args passed to Python function: scale.olm.generate.root.jt_expander",
        "",
        "    .. code:: JSON",
        "",
        "",
        "        {",
        "            \"_type\": \"scale.olm.generate.root:jt_expander\",",
        "            \"template\": \"\",",
        "            \"static\": {",
        "                \"_type\": \"scale.olm.generate.static:pass_through\",",
        "                \"addnux\": 2,",
        "                \"xslib\": \"v7.1\"",
        "            },",
        "            \"states\": {",
        "                \"_type\": \"scale.olm.generate.states:full_hypercube\",",
        "                \"coolant_density\": [",
        "                    0.4,",
        "                    0.7,",
        "                    1.0",
        "                ],",
        "                \"enrichment\": [",
        "                    1.5,",
        "                    3.5,",
        "                    4.5",
        "                ],",
        "                \"specific_power\": [",
        "                    42.0",
        "                ]",
        "            },",
        "            \"comp\": {",
        "                \"fuel\": {",
        "                    \"_type\": \"scale.olm.generate.comp:uo2_simple\"",
        "                }",
        "            },",
        "            \"time\": {",
        "                \"_type\": \"scale.olm.generate.time:constpower_burndata\",",
        "                \"gwd_burnups\": [",
        "                    0,",
        "                    10,",
        "                    30,",
        "                    60",
        "                ]",
        "            },",
        "            \"dynamic\": {",
        "                \"z1\": {",
        "                    \"_type\": \"scale.olm.generate.dynamic:scipy_interp\",",
        "                    \"state_var\": \"coolant_density\",",
        "                    \"data_pairs\": [",
        "                        [",
        "                            0.3,",
        "                            0.4",
        "                        ],",
        "                        [",
        "                            0.7,",
        "                            0.5",
        "                        ],",
        "                        [",
        "                            1.1,",
        "                            0.6",
        "                        ]",
        "                    ],",
        "                    \"method\": \"pchip\"",
        "                }",
        "            }",
        "        }",
        "",
        ".. only::latex",
        "",
        "    END Args passed to Python function: scale.olm.generate.root.jt_expander",
        "",
        "",
        "",
        ".. collapse:: Data available in template: root",
        "",
        "    .. code:: JSON",
        "",
        "",
        "        {",
        "            \"work_dir\": \"/path/to/_work\",",
        "            \"perms\": [",
        "                {",
        "                    \"static\": {",
        "                        \"addnux\": 2,",
        "                        \"xslib\": \"v7.1\"",
        "                    },",
        "                    \"comp\": {",
        "                        \"fuel\": {",
        "                            \"density\": 0.0,",
        "                            \"uo2\": {",
        "                                \"iso\": {",
        "                                    \"u235\": 1.5,",
        "                                    \"u238\": 98.5,",
        "                                    \"u234\": 1e-20,",
        "                                    \"u236\": 1e-20",
        "                                }",
        "                            },",
        "                            \"_input\": {",
        "                                \"state\": {",
        "                                    \"coolant_density\": 0.4,",
        "                                    \"enrichment\": 1.5,",
        "                                    \"specific_power\": 42.0",
        "                                },",
        "                                \"density\": 0.0",
        "                            }",
        "                        }",
        "                    },",
        "                    \"time\": {",
        "                        \"burndata\": [",
        "                            {",
        "                                \"power\": 42.0,",
        "                                \"burn\": 238.0952380952381",
        "                            },",
        "                            {",
        "                                \"power\": 42.0,",
        "                                \"burn\": 476.19047619047626",
        "                            },",
        "                            {",
        "                                \"power\": 42.0,",
        "                                \"burn\": 714.2857142857143",
        "                            },",
        "                            {",
        "                                \"power\": 42.0,",
        "                                \"burn\": 714.2857142857143",
        "                            }",
        "                        ]",
        "                    },",
        "                    \"state\": {",
        "                        \"coolant_density\": 0.4,",
        "                        \"enrichment\": 1.5,",
        "                        \"specific_power\": 42.0",
        "                    },",
        "                    \"dynamic\": {",
        "                        \"z1\": 0.42500000000000004",
        "                    },",
        "                    \"input_file\": \"perms/d2092b503116a7ab3df6e60e5bc06609/model_c06609.inp\",",
        "                    \"_\": {",
        "                        \"model\": {},",
        "                        \"data_hash\": \"d2092b503116a7ab3df6e60e5bc06609\",",
        "                        \"data_file\": \"perms/d2092b503116a7ab3df6e60e5bc06609/data.olm.json\"",
        "                    }",
        "                },",
        "                {",
        "                    \"static\": {",
        "                        \"addnux\": 2,",
        "                        \"xslib\": \"v7.1\"",
        "                    },",
        "                    \"comp\": {",
        "                        \"fuel\": {",
        "                            \"density\": 0.0,",
        "                            \"uo2\": {",
        "                                \"iso\": {",
        "                                    \"u235\": 3.5,",
        "                                    \"u238\": 96.5,",
        "                                    \"u234\": 1e-20,",
        "                                    \"u236\": 1e-20",
        "                                }",
        "                            },",
        "                            \"_input\": {",
        "                                \"state\": {",
        "                                    \"coolant_density\": 0.4,",
        "                                    \"enrichment\": 3.5,",
        "                                    \"specific_power\": 42.0",
        "                                },",
        "                                \"density\": 0.0",
        "                            }",
        "                        }",
        "                    },",
        "                    \"time\": {",
        "                        \"burndata\": [",
        "                            {",
        "                                \"power\": 42.0,",
        "                                \"burn\": 238.0952380952381",
        "                            },",
        "                            {",
        "                                \"power\": 42.0,",
        "                                \"burn\": 476.19047619047626",
        "                            },",
        "                            {",
        "                                \"power\": 42.0,",
        "                                \"burn\": 714.2857142857143",
        "                            },",
        "                            {",
        "                                \"power\": 42.0,",
        "                                \"burn\": 714.2857142857143",
        "                            }",
        "                        ]",
        "                    },",
        "                    \"state\": {",
        "                        \"coolant_density\": 0.4,",
        "                        \"enrichment\": 3.5,",
        "                        \"specific_power\": 42.0",
        "                    },",
        "                    \"dynamic\": {",
        "                        \"z1\": 0.42500000000000004",
        "                    },",
        "                    \"input_file\": \"perms/d2093369ae96c56520706a602b762acf/model_762acf.inp\",",
        "                    \"_\": {",
        "                        \"model\": {},",
        "                        \"data_hash\": \"d2093369ae96c56520706a602b762acf\",",
        "                        \"data_file\": \"perms/d2093369ae96c56520706a602b762acf/data.olm.json\"",
        "                    }",
        "                },",
        "                {",
        "                    \"static\": {",
        "                        \"addnux\": 2,",
        "                        \"xslib\": \"v7.1\"",
        "                    },",
        "                    \"comp\": {",
        "                        \"fuel\": {",
        "                            \"density\": 0.0,",
        "                            \"uo2\": {",
        "                                \"iso\": {",
        "                                    \"u235\": 4.5,",
        "                                    \"u238\": 95.5,",
        "                                    \"u234\": 1e-20,",
        "                                    \"u236\": 1e-20",
        "                                }",
        "                            },",
        "                            \"_input\": {",
        "                                \"state\": {",
        "                                    \"coolant_density\": 0.4,",
        "                                    \"enrichment\": 4.5,",
        "                                    \"specific_power\": 42.0",
        "                                },",
        "                                \"density\": 0.0",
        "                            }",
        "                        }",
        "                    },",
        "                    \"time\": {",
        "                        \"burndata\": [",
        "                            {",
        "                                \"power\": 42.0,",
        "                                \"burn\": 238.0952380952381",
        "                            },",
        "                            {",
        "                                \"power\": 42.0,",
        "                                \"burn\": 476.19047619047626",
        "                            },",
        "                            {",
        "                                \"power\": 42.0,",
        "                                \"burn\": 714.2857142857143",
        "                            },",
        "                            {",
        "                                \"power\": 42.0,",
        "                                \"burn\": 714.2857142857143",
        "                            }",
        "                        ]",
        "                    },",
        "                    \"state\": {",
        "                        \"coolant_density\": 0.4,",
        "                        \"enrichment\": 4.5,",
        "                        \"specific_power\": 42.0",
        "                    },",
        "                    \"dynamic\": {",
        "                        \"z1\": 0.42500000000000004",
        "                    },",
        "                    \"input_file\": \"perms/d209008baf0f0d1a120f160a0c756bff/model_756bff.inp\",",
        "                    \"_\": {",
        "                        \"model\": {},",
        "                        \"data_hash\": \"d209008baf0f0d1a120f160a0c756bff\",",
        "                        \"data_file\": \"perms/d209008baf0f0d1a120f160a0c756bff/data.olm.json\"",
        "                    }",
        "                },",
        "                {",
        "                    \"static\": {",
        "                        \"addnux\": 2,",
        "                        \"xslib\": \"v7.1\"",
        "                    },",
        "                    \"comp\": {",
        "                        \"fuel\": {",
        "                            \"density\": 0.0,",
        "                            \"uo2\": {",
        "                                \"iso\": {",
        "                                    \"u235\": 1.5,",
        "                                    \"u238\": 98.5,",
        "                                    \"u234\": 1e-20,",
        "                                    \"u236\": 1e-20",
        "                                }",
        "                            },",
        "                            \"_input\": {",
        "                                \"state\": {",
        "                                    \"coolant_density\": 0.7,",
        "                                    \"enrichment\": 1.5,",
        "                                    \"specific_power\": 42.0",
        "                                },",
        "                                \"density\": 0.0",
        "                            }",
        "                        }",
        "                    },",
        "                    \"time\": {",
        "                        \"burndata\": [",
        "                            {",
        "                                \"power\": 42.0,",
        "                                \"burn\": 238.0952380952381",
        "                            },",
        "                            {",
        "                                \"power\": 42.0,",
        "                                \"burn\": 476.19047619047626",
        "                            },",
        "                            {",
        "                                \"power\": 42.0,",
        "                                \"burn\": 714.2857142857143",
        "                            },",
        "                            {",
        "                                \"power\": 42.0,",
        "                                \"burn\": 714.2857142857143",
        "                            }",
        "                        ]",
        "                    },",
        "                    \"state\": {",
        "                        \"coolant_density\": 0.7,",
        "                        \"enrichment\": 1.5,",
        "                        \"specific_power\": 42.0",
        "                    },",
        "                    \"dynamic\": {",
        "                        \"z1\": 0.5",
        "                    },",
        "                    \"input_file\": \"perms/c2092fa42fef3df3bafb91f3f0dcece4/model_dcece4.inp\",",
        "                    \"_\": {",
        "                        \"model\": {},",
        "                        \"data_hash\": \"c2092fa42fef3df3bafb91f3f0dcece4\",",
        "                        \"data_file\": \"perms/c2092fa42fef3df3bafb91f3f0dcece4/data.olm.json\"",
        "                    }",
        "                },",
        "                {",
        "                    \"static\": {",
        "                        \"addnux\": 2,",
        "                        \"xslib\": \"v7.1\"",
        "                    },",
        "                    \"comp\": {",
        "                        \"fuel\": {",
        "                            \"density\": 0.0,",
        "                            \"uo2\": {",
        "                                \"iso\": {",
        "                                    \"u235\": 3.5,",
        "                                    \"u238\": 96.5,",
        "                                    \"u234\": 1e-20,",
        "                                    \"u236\": 1e-20",
        "                                }",
        "                            },",
        "                            \"_input\": {",
        "                                \"state\": {",
        "                                    \"coolant_density\": 0.7,",
        "                                    \"enrichment\": 3.5,",
        "                                    \"specific_power\": 42.0",
        "                                },",
        "                                \"density\": 0.0",
        "                            }",
        "                        }",
        "                    },",
        "                    \"time\": {",
        "                        \"burndata\": [",
        "                            {",
        "                                \"power\": 42.0,",
        "                                \"burn\": 238.0952380952381",
        "                            },",
        "                            {",
        "                                \"power\": 42.0,",
        "                                \"burn\": 476.19047619047626",
        "                            },",
        "                            {",
        "                                \"power\": 42.0,",
        "                                \"burn\": 714.2857142857143",
        "                            },",
        "                            {",
        "                                \"power\": 42.0,",
        "                                \"burn\": 714.2857142857143",
        "                            }",
        "                        ]",
        "                    },",
        "                    \"state\": {",
        "                        \"coolant_density\": 0.7,",
        "                        \"enrichment\": 3.5,",
        "                        \"specific_power\": 42.0",
        "                    },",
        "                    \"dynamic\": {",
        "                        \"z1\": 0.5",
        "                    },",
        "                    \"input_file\": \"perms/c2093ec1030b8ed99cd4ba43bbc7af62/model_c7af62.inp\",",
        "                    \"_\": {",
        "                        \"model\": {},",
        "                        \"data_hash\": \"c2093ec1030b8ed99cd4ba43bbc7af62\",",
        "                        \"data_file\": \"perms/c2093ec1030b8ed99cd4ba43bbc7af62/data.olm.json\"",
        "                    }",
        "                },",
        "                {",
        "                    \"static\": {",
        "                        \"addnux\": 2,",
        "                        \"xslib\": \"v7.1\"",
        "                    },",
        "                    \"comp\": {",
        "                        \"fuel\": {",
        "                            \"density\": 0.0,",
        "                            \"uo2\": {",
        "                                \"iso\": {",
        "                                    \"u235\": 4.5,",
        "                                    \"u238\": 95.5,",
        "                                    \"u234\": 1e-20,",
        "                                    \"u236\": 1e-20",
        "                                }",
        "                            },",
        "                            \"_input\": {",
        "                                \"state\": {",
        "                                    \"coolant_density\": 0.7,",
        "                                    \"enrichment\": 4.5,",
        "                                    \"specific_power\": 42.0",
        "                                },",
        "                                \"density\": 0.0",
        "                            }",
        "                        }",
        "                    },",
        "                    \"time\": {",
        "                        \"burndata\": [",
        "                            {",
        "                                \"power\": 42.0,",
        "                                \"burn\": 238.0952380952381",
        "                            },",
        "                            {",
        "                                \"power\": 42.0,",
        "                                \"burn\": 476.19047619047626",
        "                            },",
        "                            {",
        "                                \"power\": 42.0,",
        "                                \"burn\": 714.2857142857143",
        "                            },",
        "                            {",
        "                                \"power\": 42.0,",
        "                                \"burn\": 714.2857142857143",
        "                            }",
        "                        ]",
        "                    },",
        "                    \"state\": {",
        "                        \"coolant_density\": 0.7,",
        "                        \"enrichment\": 4.5,",
        "                        \"specific_power\": 42.0",
        "                    },",
        "                    \"dynamic\": {",
        "                        \"z1\": 0.5",
        "                    },",
        "                    \"input_file\": \"perms/c2090a8dbb76400629a45343e6e29a8a/model_e29a8a.inp\",",
        "                    \"_\": {",
        "                        \"model\": {},",
        "                        \"data_hash\": \"c2090a8dbb76400629a45343e6e29a8a\",",
        "                        \"data_file\": \"perms/c2090a8dbb76400629a45343e6e29a8a/data.olm.json\"",
        "                    }",
        "                },",
        "                {",
        "                    \"static\": {",
        "                        \"addnux\": 2,",
        "                        \"xslib\": \"v7.1\"",
        "                    },",
        "                    \"comp\": {",
        "                        \"fuel\": {",
        "                            \"density\": 0.0,",
        "                            \"uo2\": {",
        "                                \"iso\": {",
        "                                    \"u235\": 1.5,",
        "                                    \"u238\": 98.5,",
        "                                    \"u234\": 1e-20,",
        "                                    \"u236\": 1e-20",
        "                                }",
        "                            },",
        "                            \"_input\": {",
        "                                \"state\": {",
        "                                    \"coolant_density\": 1.0,",
        "                                    \"enrichment\": 1.5,",
        "                                    \"specific_power\": 42.0",
        "                                },",
        "                                \"density\": 0.0",
        "                            }",
        "                        }",
        "                    },",
        "                    \"time\": {",
        "                        \"burndata\": [",
        "                            {",
        "                                \"power\": 42.0,",
        "                                \"burn\": 238.0952380952381",
        "                            },",
        "                            {",
        "                                \"power\": 42.0,",
        "                                \"burn\": 476.19047619047626",
        "                            },",
        "                            {",
        "                                \"power\": 42.0,",
        "                                \"burn\": 714.2857142857143",
        "                            },",
        "                            {",
        "                                \"power\": 42.0,",
        "                                \"burn\": 714.2857142857143",
        "                            }",
        "                        ]",
        "                    },",
        "                    \"state\": {",
        "                        \"coolant_density\": 1.0,",
        "                        \"enrichment\": 1.5,",
        "                        \"specific_power\": 42.0",
        "                    },",
        "                    \"dynamic\": {",
        "                        \"z1\": 0.575",
        "                    },",
        "                    \"input_file\": \"perms/c409113ed66cebbcaa820e94064a8d26/model_4a8d26.inp\",",
        "                    \"_\": {",
        "                        \"model\": {},",
        "                        \"data_hash\": \"c409113ed66cebbcaa820e94064a8d26\",",
        "                        \"data_file\": \"perms/c409113ed66cebbcaa820e94064a8d26/data.olm.json\"",
        "                    }",
        "                },",
        "                {",
        "                    \"static\": {",
        "                        \"addnux\": 2,",
        "                        \"xslib\": \"v7.1\"",
        "                    },",
        "                    \"comp\": {",
        "                        \"fuel\": {",
        "                            \"density\": 0.0,",
        "                            \"uo2\": {",
        "                                \"iso\": {",
        "                                    \"u235\": 3.5,",
        "                                    \"u238\": 96.5,",
        "                                    \"u234\": 1e-20,",
        "                                    \"u236\": 1e-20",
        "                                }",
        "                            },",
        "                            \"_input\": {",
        "                                \"state\": {",
        "                                    \"coolant_density\": 1.0,",
        "                                    \"enrichment\": 3.5,",
        "                                    \"specific_power\": 42.0",
        "                                },",
        "                                \"density\": 0.0",
        "                            }",
        "                        }",
        "                    },",
        "                    \"time\": {",
        "                        \"burndata\": [",
        "                            {",
        "                                \"power\": 42.0,",
        "                                \"burn\": 238.0952380952381",
        "                            },",
        "                            {",
        "                                \"power\": 42.0,",
        "                                \"burn\": 476.19047619047626",
        "                            },",
        "                            {",
        "                                \"power\": 42.0,",
        "                                \"burn\": 714.2857142857143",
        "                            },",
        "                            {",
        "                                \"power\": 42.0,",
        "                                \"burn\": 714.2857142857143",
        "                            }",
        "                        ]",
        "                    },",
        "                    \"state\": {",
        "                        \"coolant_density\": 1.0,",
        "                        \"enrichment\": 3.5,",
        "                        \"specific_power\": 42.0",
        "                    },",
        "                    \"dynamic\": {",
        "                        \"z1\": 0.575",
        "                    },",
        "                    \"input_file\": \"perms/c4091375da9b779d0c840e6600754053/model_754053.inp\",",
        "                    \"_\": {",
        "                        \"model\": {},",
        "                        \"data_hash\": \"c4091375da9b779d0c840e6600754053\",",
        "                        \"data_file\": \"perms/c4091375da9b779d0c840e6600754053/data.olm.json\"",
        "                    }",
        "                },",
        "                {",
        "                    \"static\": {",
        "                        \"addnux\": 2,",
        "                        \"xslib\": \"v7.1\"",
        "                    },",
        "                    \"comp\": {",
        "                        \"fuel\": {",
        "                            \"density\": 0.0,",
        "                            \"uo2\": {",
        "                                \"iso\": {",
        "                                    \"u235\": 4.5,",
        "                                    \"u238\": 95.5,",
        "                                    \"u234\": 1e-20,",
        "                                    \"u236\": 1e-20",
        "                                }",
        "                            },",
        "                            \"_input\": {",
        "                                \"state\": {",
        "                                    \"coolant_density\": 1.0,",
        "                                    \"enrichment\": 4.5,",
        "                                    \"specific_power\": 42.0",
        "                                },",
        "                                \"density\": 0.0",
        "                            }",
        "                        }",
        "                    },",
        "                    \"time\": {",
        "                        \"burndata\": [",
        "                            {",
        "                                \"power\": 42.0,",
        "                                \"burn\": 238.0952380952381",
        "                            },",
        "                            {",
        "                                \"power\": 42.0,",
        "                                \"burn\": 476.19047619047626",
        "                            },",
        "                            {",
        "                                \"power\": 42.0,",
        "                                \"burn\": 714.2857142857143",
        "                            },",
        "                            {",
        "                                \"power\": 42.0,",
        "                                \"burn\": 714.2857142857143",
        "                            }",
        "                        ]",
        "                    },",
        "                    \"state\": {",
        "                        \"coolant_density\": 1.0,",
        "                        \"enrichment\": 4.5,",
        "                        \"specific_power\": 42.0",
        "                    },",
        "                    \"dynamic\": {",
        "                        \"z1\": 0.575",
        "                    },",
        "                    \"input_file\": \"perms/c409ce9da9dfe9d010a1f0cda1a022cc/model_a022cc.inp\",",
        "                    \"_\": {",
        "                        \"model\": {},",
        "                        \"data_hash\": \"c409ce9da9dfe9d010a1f0cda1a022cc\",",
        "                        \"data_file\": \"perms/c409ce9da9dfe9d010a1f0cda1a022cc/data.olm.json\"",
        "                    }",
        "                }",
        "            ],",
        "            \"static\": {",
        "                \"addnux\": 2,",
        "                \"xslib\": \"v7.1\"",
        "            }",
        "        }",
        "",
        ".. only::latex",
        "",
        "    END Data available in template: root",
        "",
        "",
        "See also: :obj:`scale.olm.generate.root.jt_expander`"
    ]
}